[
	{
		"class name":"com.sun.imageio.plugins.common.BogusColorSpace",
		"method name":"toRGB",
		"method key":"Lcom/sun/imageio/plugins/common/BogusColorSpace;.toRGB([F)[F",
		"read list":[
			{
				"name":"java.awt.color.ColorSpace.numComponents",
				"static label":0
			}
		],
		"write list":[],
		"native method list":[
			{
				"name":"java.lang.System.arraycopy",
				"static label":1
			}
		]
	},
	{
		"class name":"com.sun.imageio.plugins.common.BogusColorSpace",
		"method name":"fromRGB",
		"method key":"Lcom/sun/imageio/plugins/common/BogusColorSpace;.fromRGB([F)[F",
		"read list":[
			{
				"name":"java.awt.color.ColorSpace.numComponents",
				"static label":0
			}
		],
		"write list":[],
		"native method list":[
			{
				"name":"java.lang.System.arraycopy",
				"static label":1
			}
		]
	},
	{
		"class name":"com.sun.imageio.plugins.common.BogusColorSpace",
		"method name":"toCIEXYZ",
		"method key":"Lcom/sun/imageio/plugins/common/BogusColorSpace;.toCIEXYZ([F)[F",
		"read list":[
			{
				"name":"java.awt.color.ColorSpace.numComponents",
				"static label":0
			}
		],
		"write list":[],
		"native method list":[
			{
				"name":"java.lang.System.arraycopy",
				"static label":1
			}
		]
	},
	{
		"class name":"com.sun.imageio.plugins.common.BogusColorSpace",
		"method name":"fromCIEXYZ",
		"method key":"Lcom/sun/imageio/plugins/common/BogusColorSpace;.fromCIEXYZ([F)[F",
		"read list":[
			{
				"name":"java.awt.color.ColorSpace.numComponents",
				"static label":0
			}
		],
		"write list":[],
		"native method list":[
			{
				"name":"java.lang.System.arraycopy",
				"static label":1
			}
		]
	}
]