[
	{
		"class name":"sun.management.snmp.jvmmib.EnumJvmThreadCpuTimeMonitoring",
		"method name":"getIntTable",
		"method key":"Lsun/management/snmp/jvmmib/EnumJvmThreadCpuTimeMonitoring;.getIntTable()Ljava/util/Hashtable<Ljava/lang/Integer;Ljava/lang/String;>;",
		"read list":[
			{
				"name":"sun.management.snmp.jvmmib.EnumJvmThreadCpuTimeMonitoring.intTable",
				"static label":1
			}
		],
		"write list":[],
		"native method list":[]
	},
	{
		"class name":"sun.management.snmp.jvmmib.EnumJvmThreadCpuTimeMonitoring",
		"method name":"getStringTable",
		"method key":"Lsun/management/snmp/jvmmib/EnumJvmThreadCpuTimeMonitoring;.getStringTable()Ljava/util/Hashtable<Ljava/lang/String;Ljava/lang/Integer;>;",
		"read list":[
			{
				"name":"sun.management.snmp.jvmmib.EnumJvmThreadCpuTimeMonitoring.stringTable",
				"static label":1
			}
		],
		"write list":[],
		"native method list":[]
	}
]