[
	{
		"class name":"com.sun.jmx.snmp.SnmpScopedPduRequest",
		"method name":"setErrorIndex",
		"method key":"Lcom/sun/jmx/snmp/SnmpScopedPduRequest;.setErrorIndex(I)V",
		"read list":[
			{
				"name":"com.sun.jmx.snmp.SnmpScopedPduRequest.errorIndex",
				"static label":0
			}
		],
		"write list":[
			{
				"name":"com.sun.jmx.snmp.SnmpScopedPduRequest.errorIndex",
				"static label":0
			}
		],
		"native method list":[]
	},
	{
		"class name":"com.sun.jmx.snmp.SnmpScopedPduRequest",
		"method name":"setErrorStatus",
		"method key":"Lcom/sun/jmx/snmp/SnmpScopedPduRequest;.setErrorStatus(I)V",
		"read list":[
			{
				"name":"com.sun.jmx.snmp.SnmpScopedPduRequest.errorStatus",
				"static label":0
			}
		],
		"write list":[
			{
				"name":"com.sun.jmx.snmp.SnmpScopedPduRequest.errorStatus",
				"static label":0
			}
		],
		"native method list":[]
	},
	{
		"class name":"com.sun.jmx.snmp.SnmpScopedPduRequest",
		"method name":"getErrorIndex",
		"method key":"Lcom/sun/jmx/snmp/SnmpScopedPduRequest;.getErrorIndex()I",
		"read list":[
			{
				"name":"com.sun.jmx.snmp.SnmpScopedPduRequest.errorIndex",
				"static label":0
			}
		],
		"write list":[],
		"native method list":[]
	},
	{
		"class name":"com.sun.jmx.snmp.SnmpScopedPduRequest",
		"method name":"getErrorStatus",
		"method key":"Lcom/sun/jmx/snmp/SnmpScopedPduRequest;.getErrorStatus()I",
		"read list":[
			{
				"name":"com.sun.jmx.snmp.SnmpScopedPduRequest.errorStatus",
				"static label":0
			}
		],
		"write list":[],
		"native method list":[]
	},
	{
		"class name":"com.sun.jmx.snmp.SnmpScopedPduRequest",
		"method name":"getResponsePdu",
		"method key":"Lcom/sun/jmx/snmp/SnmpScopedPduRequest;.getResponsePdu()Lcom/sun/jmx/snmp/SnmpPdu;",
		"read list":[
			{
				"name":"com.sun.jmx.snmp.SnmpPdu.version",
				"static label":0
			},
			{
				"name":"com.sun.jmx.snmp.SnmpScopedPduPacket.msgFlags",
				"static label":0
			},
			{
				"name":"com.sun.jmx.snmp.SnmpPdu.port",
				"static label":0
			},
			{
				"name":"com.sun.jmx.snmp.SnmpPdu.requestId",
				"static label":0
			},
			{
				"name":"com.sun.jmx.snmp.SnmpScopedPduRequest.errorStatus",
				"static label":0
			},
			{
				"name":"com.sun.jmx.snmp.SnmpScopedPduPacket.msgMaxSize",
				"static label":0
			},
			{
				"name":"com.sun.jmx.snmp.SnmpScopedPduPacket.msgId",
				"static label":0
			},
			{
				"name":"com.sun.jmx.snmp.SnmpPdu.type",
				"static label":0
			},
			{
				"name":"com.sun.jmx.snmp.SnmpPdu.address",
				"static label":0
			},
			{
				"name":"com.sun.jmx.snmp.SnmpScopedPduPacket.securityParameters",
				"static label":0
			},
			{
				"name":"com.sun.jmx.snmp.SnmpScopedPduPacket.msgSecurityModel",
				"static label":0
			},
			{
				"name":"com.sun.jmx.snmp.SnmpScopedPduRequest.errorIndex",
				"static label":0
			}
		],
		"write list":[],
		"native method list":[]
	}
]