[
	{
		"before commit":"176fa070c1e2ea3b0737c8150a1302e4cb643816",
		"after commit":"af2afeb641ec729b1dbb505be9471d0f422f8dda",
		"file path":"core/src/main/java/hivemall/smile/classification/DecisionTree.java",
		"old name":"x.get(splitFeature,Double.NaN)",
		"new name":"feature",
		"type":"double",
		"variable place":{
			"start line":328,
			"start column":30,
			"end line":328,
			"end column":71
		},
		"before location list":[
			{
				"start line":331,
				"start column":21,
				"end line":335,
				"end column":22
			},
			{
				"start line":325,
				"start column":21,
				"end line":329,
				"end column":22
			}
		],
		"after location list":[
			{
				"start line":330,
				"start column":21,
				"end line":336,
				"end column":22
			},
			{
				"start line":338,
				"start column":21,
				"end line":344,
				"end column":22
			}
		]
	},
	{
		"before commit":"028306e77cba45e587429412405b71339cab411b",
		"after commit":"8c3631df038c4550de22b92c47b160f8881c25f7",
		"file path":"core/src/main/java/hivemall/ftvec/binning/FeatureBinningUDF.java",
		"old name":"args[1].get()",
		"new name":"arg1",
		"type":"Object",
		"variable place":{
			"start line":171,
			"start column":22,
			"end line":171,
			"end column":42
		},
		"before location list":[
			{
				"start line":166,
				"start column":17,
				"end line":166,
				"end column":93
			},
			{
				"start line":129,
				"start column":17,
				"end line":129,
				"end column":86
			}
		],
		"after location list":[
			{
				"start line":179,
				"start column":17,
				"end line":179,
				"end column":67
			},
			{
				"start line":209,
				"start column":17,
				"end line":209,
				"end column":89
			}
		]
	},
	{
		"before commit":"47d1100c1fab6796f09f0998624b3a445869f1d4",
		"after commit":"30593b14b4006feb0c01e27321830251b7aeb703",
		"file path":"core/src/main/java/hivemall/topicmodel/ProbabilisticTopicModelBaseUDTF.java",
		"old name":"args[0]",
		"new name":"arg0",
		"type":"Object",
		"variable place":{
			"start line":165,
			"start column":16,
			"end line":165,
			"end column":30
		},
		"before location list":[
			{
				"start line":162,
				"start column":9,
				"end line":162,
				"end column":64
			},
			{
				"start line":166,
				"start column":13,
				"end line":166,
				"end column":64
			}
		],
		"after location list":[
			{
				"start line":174,
				"start column":13,
				"end line":174,
				"end column":61
			},
			{
				"start line":170,
				"start column":9,
				"end line":170,
				"end column":61
			}
		]
	},
	{
		"before commit":"4ca1c19c7e00120cb0abd42d6c1f1b48176846e8",
		"after commit":"f8beee36b36274d8eb8948f6838aacd955817eba",
		"file path":"core/src/main/java/hivemall/GeneralLearnerBaseUDTF.java",
		"old name":"probe.get()",
		"new name":"v",
		"type":"float",
		"variable place":{
			"start line":716,
			"start column":29,
			"end line":716,
			"end column":44
		},
		"before location list":[
			{
				"start line":724,
				"start column":17,
				"end line":724,
				"end column":37
			},
			{
				"start line":705,
				"start column":17,
				"end line":705,
				"end column":37
			}
		],
		"after location list":[
			{
				"start line":721,
				"start column":17,
				"end line":721,
				"end column":27
			},
			{
				"start line":744,
				"start column":17,
				"end line":744,
				"end column":27
			}
		]
	},
	{
		"before commit":"4ca1c19c7e00120cb0abd42d6c1f1b48176846e8",
		"after commit":"f8beee36b36274d8eb8948f6838aacd955817eba",
		"file path":"core/src/main/java/hivemall/GeneralLearnerBaseUDTF.java",
		"old name":"probe.get()",
		"new name":"v",
		"type":"float",
		"variable place":{
			"start line":740,
			"start column":29,
			"end line":740,
			"end column":44
		},
		"before location list":[
			{
				"start line":724,
				"start column":17,
				"end line":724,
				"end column":37
			},
			{
				"start line":705,
				"start column":17,
				"end line":705,
				"end column":37
			}
		],
		"after location list":[
			{
				"start line":744,
				"start column":17,
				"end line":744,
				"end column":27
			},
			{
				"start line":721,
				"start column":17,
				"end line":721,
				"end column":27
			}
		]
	},
	{
		"before commit":"3804789168dab5c5d43aac1fd4000e07688c6a06",
		"after commit":"7205de1e959f0d9b96ac756e415d8a8ada7e92af",
		"file path":"core/src/main/java/hivemall/utils/collections/maps/OpenHashMap.java",
		"old name":"existingKeys[x]",
		"new name":"k",
		"type":"K",
		"variable place":{
			"start line":324,
			"start column":25,
			"end line":324,
			"end column":44
		},
		"before location list":[
			{
				"start line":276,
				"start column":21,
				"end line":276,
				"end column":61
			},
			{
				"start line":275,
				"start column":17,
				"end line":277,
				"end column":18
			}
		],
		"after location list":[
			{
				"start line":325,
				"start column":17,
				"end line":327,
				"end column":18
			},
			{
				"start line":326,
				"start column":21,
				"end line":326,
				"end column":47
			}
		]
	},
	{
		"before commit":"e3bbaf622a06a07c3f15792f2b1e9a3bb3bb2e78",
		"after commit":"04372d490194d598bbc79ec1adba8b0918225c38",
		"file path":"xgboost/src/main/java/hivemall/xgboost/tools/XGBoostMulticlassPredictUDTF.java",
		"old name":"predicted[i]",
		"new name":"predicted_i",
		"type":"float[]",
		"variable place":{
			"start line":67,
			"start column":27,
			"end line":67,
			"end column":53
		},
		"before location list":[
			{
				"start line":60,
				"start column":17,
				"end line":60,
				"end column":46
			},
			{
				"start line":57,
				"start column":13,
				"end line":57,
				"end column":46
			},
			{
				"start line":59,
				"start column":13,
				"end line":62,
				"end column":14
			}
		],
		"after location list":[
			{
				"start line":71,
				"start column":13,
				"end line":71,
				"end column":45
			},
			{
				"start line":72,
				"start column":13,
				"end line":77,
				"end column":14
			},
			{
				"start line":74,
				"start column":17,
				"end line":74,
				"end column":45
			}
		]
	},
	{
		"before commit":"50b4c9a752b3d3f99a1e519c609176fc46debe69",
		"after commit":"3848ea60a76cb4b9df7f975bd90e71cd46c77faa",
		"file path":"core/src/main/java/hivemall/optimizer/Optimizer.java",
		"old name":"weight.get()",
		"new name":"oldWeight",
		"type":"float",
		"variable place":{
			"start line":72,
			"start column":19,
			"end line":72,
			"end column":43
		},
		"before location list":[
			{
				"start line":68,
				"start column":13,
				"end line":68,
				"end column":73
			},
			{
				"start line":66,
				"start column":13,
				"end line":66,
				"end column":63
			}
		],
		"after location list":[
			{
				"start line":73,
				"start column":13,
				"end line":73,
				"end column":60
			},
			{
				"start line":75,
				"start column":13,
				"end line":75,
				"end column":70
			}
		]
	},
	{
		"before commit":"e273078982261d7e9eb5cd93cebe1ca8a3c1c5e9",
		"after commit":"211c28036e4a7e7549b3e21fae723f207d85aa09",
		"file path":"core/src/main/java/hivemall/utils/math/MathUtils.java",
		"old name":"arr.length",
		"new name":"size",
		"type":"int",
		"variable place":{
			"start line":414,
			"start column":13,
			"end line":414,
			"end column":30
		},
		"before location list":[
			{
				"start line":417,
				"start column":9,
				"end line":419,
				"end column":10
			},
			{
				"start line":414,
				"start column":9,
				"end line":416,
				"end column":10
			}
		],
		"after location list":[
			{
				"start line":421,
				"start column":9,
				"end line":423,
				"end column":10
			},
			{
				"start line":415,
				"start column":9,
				"end line":417,
				"end column":10
			}
		]
	},
	{
		"before commit":"8dc3a024d9b2708f297a886a3256e7107bc276f9",
		"after commit":"7956b5f289a481e25f701dd38f8f1f281e68baaf",
		"file path":"core/src/main/java/hivemall/smile/classification/DecisionTree.java",
		"old name":"count[i]",
		"new name":"count_i",
		"type":"int",
		"variable place":{
			"start line":780,
			"start column":31,
			"end line":780,
			"end column":49
		},
		"before location list":[
			{
				"start line":734,
				"start column":21,
				"end line":737,
				"end column":22
			},
			{
				"start line":744,
				"start column":25,
				"end line":744,
				"end column":58
			},
			{
				"start line":735,
				"start column":25,
				"end line":735,
				"end column":58
			},
			{
				"start line":743,
				"start column":21,
				"end line":746,
				"end column":22
			},
			{
				"start line":753,
				"start column":21,
				"end line":755,
				"end column":22
			}
		],
		"after location list":[
			{
				"start line":782,
				"start column":25,
				"end line":782,
				"end column":57
			},
			{
				"start line":792,
				"start column":25,
				"end line":792,
				"end column":57
			},
			{
				"start line":791,
				"start column":21,
				"end line":794,
				"end column":22
			},
			{
				"start line":802,
				"start column":21,
				"end line":804,
				"end column":22
			},
			{
				"start line":781,
				"start column":21,
				"end line":784,
				"end column":22
			}
		]
	},
	{
		"before commit":"8dc3a024d9b2708f297a886a3256e7107bc276f9",
		"after commit":"7956b5f289a481e25f701dd38f8f1f281e68baaf",
		"file path":"core/src/main/java/hivemall/smile/classification/DecisionTree.java",
		"old name":"count[i]",
		"new name":"count_i",
		"type":"int",
		"variable place":{
			"start line":790,
			"start column":31,
			"end line":790,
			"end column":49
		},
		"before location list":[
			{
				"start line":734,
				"start column":21,
				"end line":737,
				"end column":22
			},
			{
				"start line":744,
				"start column":25,
				"end line":744,
				"end column":58
			},
			{
				"start line":735,
				"start column":25,
				"end line":735,
				"end column":58
			},
			{
				"start line":743,
				"start column":21,
				"end line":746,
				"end column":22
			},
			{
				"start line":753,
				"start column":21,
				"end line":755,
				"end column":22
			}
		],
		"after location list":[
			{
				"start line":792,
				"start column":25,
				"end line":792,
				"end column":57
			},
			{
				"start line":782,
				"start column":25,
				"end line":782,
				"end column":57
			},
			{
				"start line":791,
				"start column":21,
				"end line":794,
				"end column":22
			},
			{
				"start line":802,
				"start column":21,
				"end line":804,
				"end column":22
			},
			{
				"start line":781,
				"start column":21,
				"end line":784,
				"end column":22
			}
		]
	},
	{
		"before commit":"8dc3a024d9b2708f297a886a3256e7107bc276f9",
		"after commit":"7956b5f289a481e25f701dd38f8f1f281e68baaf",
		"file path":"core/src/main/java/hivemall/smile/classification/DecisionTree.java",
		"old name":"count[i]",
		"new name":"count_i",
		"type":"int",
		"variable place":{
			"start line":801,
			"start column":31,
			"end line":801,
			"end column":49
		},
		"before location list":[
			{
				"start line":734,
				"start column":21,
				"end line":737,
				"end column":22
			},
			{
				"start line":744,
				"start column":25,
				"end line":744,
				"end column":58
			},
			{
				"start line":735,
				"start column":25,
				"end line":735,
				"end column":58
			},
			{
				"start line":743,
				"start column":21,
				"end line":746,
				"end column":22
			},
			{
				"start line":753,
				"start column":21,
				"end line":755,
				"end column":22
			}
		],
		"after location list":[
			{
				"start line":782,
				"start column":25,
				"end line":782,
				"end column":57
			},
			{
				"start line":792,
				"start column":25,
				"end line":792,
				"end column":57
			},
			{
				"start line":802,
				"start column":21,
				"end line":804,
				"end column":22
			},
			{
				"start line":791,
				"start column":21,
				"end line":794,
				"end column":22
			},
			{
				"start line":781,
				"start column":21,
				"end line":784,
				"end column":22
			}
		]
	},
	{
		"before commit":"4d17e9855bab5da560641b09c9733d0bb21080e3",
		"after commit":"c87acb36fe5bae379b2f09e83681b3351ddea6b9",
		"file path":"core/src/main/java/hivemall/ftvec/ranking/PopulateNotInUDTF.java",
		"old name":"args[0]",
		"new name":"arg0",
		"type":"Object",
		"variable place":{
			"start line":113,
			"start column":16,
			"end line":113,
			"end column":30
		},
		"before location list":[
			{
				"start line":125,
				"start column":13,
				"end line":125,
				"end column":66
			},
			{
				"start line":115,
				"start column":13,
				"end line":115,
				"end column":79
			}
		],
		"after location list":[
			{
				"start line":130,
				"start column":13,
				"end line":130,
				"end column":63
			},
			{
				"start line":120,
				"start column":13,
				"end line":120,
				"end column":76
			}
		]
	},
	{
		"before commit":"80e96d28b15735f5454854cc45a64ecee6dd6fc3",
		"after commit":"245c7c3db98f2db8395669aabca0b04988758025",
		"file path":"core/src/main/java/hivemall/smile/regression/RegressionTree.java",
		"old name":"samples[i]",
		"new name":"sample",
		"type":"int",
		"variable place":{
			"start line":565,
			"start column":31,
			"end line":565,
			"end column":50
		},
		"before location list":[
			{
				"start line":570,
				"start column":29,
				"end line":570,
				"end column":58
			},
			{
				"start line":567,
				"start column":21,
				"end line":608,
				"end column":22
			},
			{
				"start line":580,
				"start column":29,
				"end line":580,
				"end column":58
			},
			{
				"start line":606,
				"start column":25,
				"end line":606,
				"end column":54
			},
			{
				"start line":571,
				"start column":29,
				"end line":571,
				"end column":53
			},
			{
				"start line":581,
				"start column":29,
				"end line":581,
				"end column":53
			},
			{
				"start line":607,
				"start column":25,
				"end line":607,
				"end column":49
			}
		],
		"after location list":[
			{
				"start line":580,
				"start column":29,
				"end line":580,
				"end column":49
			},
			{
				"start line":569,
				"start column":29,
				"end line":569,
				"end column":54
			},
			{
				"start line":605,
				"start column":25,
				"end line":605,
				"end column":50
			},
			{
				"start line":566,
				"start column":21,
				"end line":607,
				"end column":22
			},
			{
				"start line":606,
				"start column":25,
				"end line":606,
				"end column":45
			},
			{
				"start line":570,
				"start column":29,
				"end line":570,
				"end column":49
			},
			{
				"start line":579,
				"start column":29,
				"end line":579,
				"end column":54
			}
		]
	},
	{
		"before commit":"f6ff7a44e2bfcbd9eb2b6bef3c7fe87fc551e1ef",
		"after commit":"2a8f0131117dae02bd95d3230f516ad9b2fd0842",
		"file path":"core/src/main/java/hivemall/smile/classification/GradientTreeBoostingClassifierUDTF.java",
		"old name":"y[i]",
		"new name":"y_i",
		"type":"double",
		"variable place":{
			"start line":624,
			"start column":28,
			"end line":624,
			"end column":38
		},
		"before location list":[
			{
				"start line":616,
				"start column":21,
				"end line":616,
				"end column":49
			},
			{
				"start line":617,
				"start column":21,
				"end line":617,
				"end column":32
			}
		],
		"after location list":[
			{
				"start line":626,
				"start column":21,
				"end line":626,
				"end column":31
			},
			{
				"start line":625,
				"start column":21,
				"end line":625,
				"end column":48
			}
		]
	},
	{
		"before commit":"f6ff7a44e2bfcbd9eb2b6bef3c7fe87fc551e1ef",
		"after commit":"2a8f0131117dae02bd95d3230f516ad9b2fd0842",
		"file path":"core/src/main/java/hivemall/smile/classification/GradientTreeBoostingClassifierUDTF.java",
		"old name":"y[i]",
		"new name":"y_i",
		"type":"double",
		"variable place":{
			"start line":668,
			"start column":28,
			"end line":668,
			"end column":38
		},
		"before location list":[
			{
				"start line":660,
				"start column":21,
				"end line":660,
				"end column":32
			},
			{
				"start line":659,
				"start column":21,
				"end line":659,
				"end column":49
			}
		],
		"after location list":[
			{
				"start line":669,
				"start column":21,
				"end line":669,
				"end column":48
			},
			{
				"start line":670,
				"start column":21,
				"end line":670,
				"end column":31
			}
		]
	},
	{
		"before commit":"bf143a09a8b831f1ae6216a028c33be08448b3fc",
		"after commit":"fe91f6f4f352844b1b4975ead504c5d335778019",
		"file path":"core/src/main/java/hivemall/smile/classification/GradientTreeBoostingClassifierUDTF.java",
		"old name":"y[i]",
		"new name":"y_i",
		"type":"double",
		"variable place":{
			"start line":624,
			"start column":28,
			"end line":624,
			"end column":38
		},
		"before location list":[
			{
				"start line":616,
				"start column":21,
				"end line":616,
				"end column":49
			},
			{
				"start line":617,
				"start column":21,
				"end line":617,
				"end column":32
			}
		],
		"after location list":[
			{
				"start line":626,
				"start column":21,
				"end line":626,
				"end column":31
			},
			{
				"start line":625,
				"start column":21,
				"end line":625,
				"end column":48
			}
		]
	},
	{
		"before commit":"bf143a09a8b831f1ae6216a028c33be08448b3fc",
		"after commit":"fe91f6f4f352844b1b4975ead504c5d335778019",
		"file path":"core/src/main/java/hivemall/smile/classification/GradientTreeBoostingClassifierUDTF.java",
		"old name":"y[i]",
		"new name":"y_i",
		"type":"double",
		"variable place":{
			"start line":668,
			"start column":28,
			"end line":668,
			"end column":38
		},
		"before location list":[
			{
				"start line":660,
				"start column":21,
				"end line":660,
				"end column":32
			},
			{
				"start line":659,
				"start column":21,
				"end line":659,
				"end column":49
			}
		],
		"after location list":[
			{
				"start line":669,
				"start column":21,
				"end line":669,
				"end column":48
			},
			{
				"start line":670,
				"start column":21,
				"end line":670,
				"end column":31
			}
		]
	},
	{
		"before commit":"f5ae2505428ad192dc0b20130149c192abc5423f",
		"after commit":"db426e58b309d52de94230136f28c911ec1f39ba",
		"file path":"core/src/main/java/hivemall/smile/classification/DecisionTree.java",
		"old name":"samples[i]",
		"new name":"sample",
		"type":"int",
		"variable place":{
			"start line":476,
			"start column":27,
			"end line":476,
			"end column":46
		},
		"before location list":[
			{
				"start line":412,
				"start column":21,
				"end line":412,
				"end column":47
			},
			{
				"start line":410,
				"start column":17,
				"end line":413,
				"end column":18
			},
			{
				"start line":411,
				"start column":21,
				"end line":411,
				"end column":37
			}
		],
		"after location list":[
			{
				"start line":477,
				"start column":17,
				"end line":480,
				"end column":18
			},
			{
				"start line":479,
				"start column":21,
				"end line":479,
				"end column":43
			},
			{
				"start line":478,
				"start column":21,
				"end line":478,
				"end column":33
			}
		]
	},
	{
		"before commit":"f5ae2505428ad192dc0b20130149c192abc5423f",
		"after commit":"db426e58b309d52de94230136f28c911ec1f39ba",
		"file path":"core/src/main/java/hivemall/smile/classification/DecisionTree.java",
		"old name":"(int)x[i][j]",
		"new name":"x_ij",
		"type":"int",
		"variable place":{
			"start line":530,
			"start column":29,
			"end line":530,
			"end column":49
		},
		"before location list":[
			{
				"start line":516,
				"start column":29,
				"end line":516,
				"end column":45
			},
			{
				"start line":504,
				"start column":25,
				"end line":509,
				"end column":26
			},
			{
				"start line":505,
				"start column":29,
				"end line":505,
				"end column":45
			},
			{
				"start line":534,
				"start column":29,
				"end line":534,
				"end column":74
			},
			{
				"start line":540,
				"start column":25,
				"end line":540,
				"end column":41
			}
		],
		"after location list":[
			{
				"start line":613,
				"start column":25,
				"end line":613,
				"end column":38
			},
			{
				"start line":575,
				"start column":25,
				"end line":580,
				"end column":26
			},
			{
				"start line":587,
				"start column":29,
				"end line":587,
				"end column":42
			},
			{
				"start line":607,
				"start column":29,
				"end line":607,
				"end column":73
			},
			{
				"start line":576,
				"start column":29,
				"end line":576,
				"end column":42
			}
		]
	},
	{
		"before commit":"f5ae2505428ad192dc0b20130149c192abc5423f",
		"after commit":"db426e58b309d52de94230136f28c911ec1f39ba",
		"file path":"core/src/main/java/hivemall/smile/classification/DecisionTree.java",
		"old name":"y[i]",
		"new name":"y_i",
		"type":"int",
		"variable place":{
			"start line":573,
			"start column":35,
			"end line":573,
			"end column":45
		},
		"before location list":[
			{
				"start line":506,
				"start column":29,
				"end line":506,
				"end column":42
			},
			{
				"start line":542,
				"start column":25,
				"end line":542,
				"end column":55
			},
			{
				"start line":541,
				"start column":25,
				"end line":541,
				"end column":38
			},
			{
				"start line":507,
				"start column":29,
				"end line":507,
				"end column":59
			},
			{
				"start line":517,
				"start column":29,
				"end line":517,
				"end column":42
			},
			{
				"start line":518,
				"start column":29,
				"end line":518,
				"end column":59
			},
			{
				"start line":504,
				"start column":25,
				"end line":509,
				"end column":26
			}
		],
		"after location list":[
			{
				"start line":577,
				"start column":29,
				"end line":577,
				"end column":41
			},
			{
				"start line":589,
				"start column":29,
				"end line":589,
				"end column":54
			},
			{
				"start line":588,
				"start column":29,
				"end line":588,
				"end column":41
			},
			{
				"start line":578,
				"start column":29,
				"end line":578,
				"end column":54
			},
			{
				"start line":575,
				"start column":25,
				"end line":580,
				"end column":26
			},
			{
				"start line":614,
				"start column":25,
				"end line":614,
				"end column":37
			},
			{
				"start line":615,
				"start column":25,
				"end line":615,
				"end column":50
			}
		]
	},
	{
		"before commit":"f5ae2505428ad192dc0b20130149c192abc5423f",
		"after commit":"db426e58b309d52de94230136f28c911ec1f39ba",
		"file path":"core/src/main/java/hivemall/smile/classification/DecisionTree.java",
		"old name":"samples[i]",
		"new name":"sample",
		"type":"int",
		"variable place":{
			"start line":570,
			"start column":31,
			"end line":570,
			"end column":50
		},
		"before location list":[
			{
				"start line":542,
				"start column":25,
				"end line":542,
				"end column":55
			},
			{
				"start line":503,
				"start column":21,
				"end line":543,
				"end column":22
			},
			{
				"start line":507,
				"start column":29,
				"end line":507,
				"end column":59
			},
			{
				"start line":518,
				"start column":29,
				"end line":518,
				"end column":59
			}
		],
		"after location list":[
			{
				"start line":589,
				"start column":29,
				"end line":589,
				"end column":54
			},
			{
				"start line":578,
				"start column":29,
				"end line":578,
				"end column":54
			},
			{
				"start line":615,
				"start column":25,
				"end line":615,
				"end column":50
			},
			{
				"start line":571,
				"start column":21,
				"end line":616,
				"end column":22
			}
		]
	},
	{
		"before commit":"f5ae2505428ad192dc0b20130149c192abc5423f",
		"after commit":"db426e58b309d52de94230136f28c911ec1f39ba",
		"file path":"core/src/main/java/hivemall/smile/classification/DecisionTree.java",
		"old name":"x[i][j]",
		"new name":"x_ij",
		"type":"double",
		"variable place":{
			"start line":572,
			"start column":38,
			"end line":572,
			"end column":52
		},
		"before location list":[
			{
				"start line":516,
				"start column":29,
				"end line":516,
				"end column":45
			},
			{
				"start line":504,
				"start column":25,
				"end line":509,
				"end column":26
			},
			{
				"start line":534,
				"start column":29,
				"end line":534,
				"end column":74
			},
			{
				"start line":505,
				"start column":29,
				"end line":505,
				"end column":45
			},
			{
				"start line":540,
				"start column":25,
				"end line":540,
				"end column":41
			}
		],
		"after location list":[
			{
				"start line":613,
				"start column":25,
				"end line":613,
				"end column":38
			},
			{
				"start line":575,
				"start column":25,
				"end line":580,
				"end column":26
			},
			{
				"start line":607,
				"start column":29,
				"end line":607,
				"end column":73
			},
			{
				"start line":587,
				"start column":29,
				"end line":587,
				"end column":42
			},
			{
				"start line":576,
				"start column":29,
				"end line":576,
				"end column":42
			}
		]
	},
	{
		"before commit":"f5ae2505428ad192dc0b20130149c192abc5423f",
		"after commit":"db426e58b309d52de94230136f28c911ec1f39ba",
		"file path":"core/src/main/java/hivemall/smile/classification/DecisionTree.java",
		"old name":"samples[i]",
		"new name":"sample",
		"type":"int",
		"variable place":{
			"start line":642,
			"start column":31,
			"end line":642,
			"end column":50
		},
		"before location list":[
			{
				"start line":570,
				"start column":21,
				"end line":578,
				"end column":22
			},
			{
				"start line":585,
				"start column":29,
				"end line":585,
				"end column":46
			},
			{
				"start line":576,
				"start column":29,
				"end line":576,
				"end column":46
			},
			{
				"start line":587,
				"start column":29,
				"end line":587,
				"end column":58
			},
			{
				"start line":572,
				"start column":29,
				"end line":572,
				"end column":57
			},
			{
				"start line":575,
				"start column":29,
				"end line":575,
				"end column":58
			},
			{
				"start line":588,
				"start column":29,
				"end line":588,
				"end column":46
			},
			{
				"start line":584,
				"start column":29,
				"end line":584,
				"end column":57
			},
			{
				"start line":582,
				"start column":21,
				"end line":590,
				"end column":22
			}
		],
		"after location list":[
			{
				"start line":648,
				"start column":29,
				"end line":648,
				"end column":54
			},
			{
				"start line":661,
				"start column":29,
				"end line":661,
				"end column":54
			},
			{
				"start line":649,
				"start column":29,
				"end line":649,
				"end column":42
			},
			{
				"start line":658,
				"start column":29,
				"end line":658,
				"end column":53
			},
			{
				"start line":662,
				"start column":29,
				"end line":662,
				"end column":42
			},
			{
				"start line":659,
				"start column":29,
				"end line":659,
				"end column":42
			},
			{
				"start line":643,
				"start column":21,
				"end line":651,
				"end column":22
			},
			{
				"start line":656,
				"start column":21,
				"end line":664,
				"end column":22
			},
			{
				"start line":645,
				"start column":29,
				"end line":645,
				"end column":53
			}
		]
	},
	{
		"before commit":"f5ae2505428ad192dc0b20130149c192abc5423f",
		"after commit":"db426e58b309d52de94230136f28c911ec1f39ba",
		"file path":"core/src/main/java/hivemall/smile/classification/DecisionTree.java",
		"old name":"samples[i]",
		"new name":"sample",
		"type":"int",
		"variable place":{
			"start line":655,
			"start column":31,
			"end line":655,
			"end column":50
		},
		"before location list":[
			{
				"start line":570,
				"start column":21,
				"end line":578,
				"end column":22
			},
			{
				"start line":585,
				"start column":29,
				"end line":585,
				"end column":46
			},
			{
				"start line":576,
				"start column":29,
				"end line":576,
				"end column":46
			},
			{
				"start line":587,
				"start column":29,
				"end line":587,
				"end column":58
			},
			{
				"start line":572,
				"start column":29,
				"end line":572,
				"end column":57
			},
			{
				"start line":575,
				"start column":29,
				"end line":575,
				"end column":58
			},
			{
				"start line":588,
				"start column":29,
				"end line":588,
				"end column":46
			},
			{
				"start line":584,
				"start column":29,
				"end line":584,
				"end column":57
			},
			{
				"start line":582,
				"start column":21,
				"end line":590,
				"end column":22
			}
		],
		"after location list":[
			{
				"start line":661,
				"start column":29,
				"end line":661,
				"end column":54
			},
			{
				"start line":648,
				"start column":29,
				"end line":648,
				"end column":54
			},
			{
				"start line":649,
				"start column":29,
				"end line":649,
				"end column":42
			},
			{
				"start line":658,
				"start column":29,
				"end line":658,
				"end column":53
			},
			{
				"start line":662,
				"start column":29,
				"end line":662,
				"end column":42
			},
			{
				"start line":659,
				"start column":29,
				"end line":659,
				"end column":42
			},
			{
				"start line":656,
				"start column":21,
				"end line":664,
				"end column":22
			},
			{
				"start line":643,
				"start column":21,
				"end line":651,
				"end column":22
			},
			{
				"start line":645,
				"start column":29,
				"end line":645,
				"end column":53
			}
		]
	},
	{
		"before commit":"c3e3f337501176070e80b5b8f2148628fe189d60",
		"after commit":"19695479da860f35e1b14757ad4b244d9a975255",
		"file path":"core/src/main/java/hivemall/smile/classification/DecisionTree.java",
		"old name":"samples[i]",
		"new name":"sample",
		"type":"int",
		"variable place":{
			"start line":476,
			"start column":27,
			"end line":476,
			"end column":46
		},
		"before location list":[
			{
				"start line":477,
				"start column":21,
				"end line":477,
				"end column":37
			},
			{
				"start line":478,
				"start column":21,
				"end line":478,
				"end column":47
			},
			{
				"start line":476,
				"start column":17,
				"end line":479,
				"end column":18
			}
		],
		"after location list":[
			{
				"start line":477,
				"start column":17,
				"end line":480,
				"end column":18
			},
			{
				"start line":479,
				"start column":21,
				"end line":479,
				"end column":43
			},
			{
				"start line":478,
				"start column":21,
				"end line":478,
				"end column":33
			}
		]
	},
	{
		"before commit":"c3e3f337501176070e80b5b8f2148628fe189d60",
		"after commit":"19695479da860f35e1b14757ad4b244d9a975255",
		"file path":"core/src/main/java/hivemall/smile/classification/DecisionTree.java",
		"old name":"samples[i]",
		"new name":"sample",
		"type":"int",
		"variable place":{
			"start line":570,
			"start column":31,
			"end line":570,
			"end column":50
		},
		"before location list":[
			{
				"start line":613,
				"start column":25,
				"end line":613,
				"end column":54
			},
			{
				"start line":587,
				"start column":29,
				"end line":587,
				"end column":58
			},
			{
				"start line":576,
				"start column":29,
				"end line":576,
				"end column":58
			},
			{
				"start line":569,
				"start column":21,
				"end line":614,
				"end column":22
			}
		],
		"after location list":[
			{
				"start line":589,
				"start column":29,
				"end line":589,
				"end column":54
			},
			{
				"start line":578,
				"start column":29,
				"end line":578,
				"end column":54
			},
			{
				"start line":615,
				"start column":25,
				"end line":615,
				"end column":50
			},
			{
				"start line":571,
				"start column":21,
				"end line":616,
				"end column":22
			}
		]
	},
	{
		"before commit":"c3e3f337501176070e80b5b8f2148628fe189d60",
		"after commit":"19695479da860f35e1b14757ad4b244d9a975255",
		"file path":"core/src/main/java/hivemall/smile/classification/DecisionTree.java",
		"old name":"samples[i]",
		"new name":"sample",
		"type":"int",
		"variable place":{
			"start line":642,
			"start column":31,
			"end line":642,
			"end column":50
		},
		"before location list":[
			{
				"start line":642,
				"start column":29,
				"end line":642,
				"end column":57
			},
			{
				"start line":658,
				"start column":29,
				"end line":658,
				"end column":46
			},
			{
				"start line":654,
				"start column":29,
				"end line":654,
				"end column":57
			},
			{
				"start line":646,
				"start column":29,
				"end line":646,
				"end column":46
			},
			{
				"start line":640,
				"start column":21,
				"end line":648,
				"end column":22
			},
			{
				"start line":655,
				"start column":29,
				"end line":655,
				"end column":46
			},
			{
				"start line":645,
				"start column":29,
				"end line":645,
				"end column":58
			},
			{
				"start line":652,
				"start column":21,
				"end line":660,
				"end column":22
			},
			{
				"start line":657,
				"start column":29,
				"end line":657,
				"end column":58
			}
		],
		"after location list":[
			{
				"start line":648,
				"start column":29,
				"end line":648,
				"end column":54
			},
			{
				"start line":661,
				"start column":29,
				"end line":661,
				"end column":54
			},
			{
				"start line":649,
				"start column":29,
				"end line":649,
				"end column":42
			},
			{
				"start line":658,
				"start column":29,
				"end line":658,
				"end column":53
			},
			{
				"start line":662,
				"start column":29,
				"end line":662,
				"end column":42
			},
			{
				"start line":659,
				"start column":29,
				"end line":659,
				"end column":42
			},
			{
				"start line":643,
				"start column":21,
				"end line":651,
				"end column":22
			},
			{
				"start line":656,
				"start column":21,
				"end line":664,
				"end column":22
			},
			{
				"start line":645,
				"start column":29,
				"end line":645,
				"end column":53
			}
		]
	},
	{
		"before commit":"c3e3f337501176070e80b5b8f2148628fe189d60",
		"after commit":"19695479da860f35e1b14757ad4b244d9a975255",
		"file path":"core/src/main/java/hivemall/smile/classification/DecisionTree.java",
		"old name":"samples[i]",
		"new name":"sample",
		"type":"int",
		"variable place":{
			"start line":655,
			"start column":31,
			"end line":655,
			"end column":50
		},
		"before location list":[
			{
				"start line":642,
				"start column":29,
				"end line":642,
				"end column":57
			},
			{
				"start line":658,
				"start column":29,
				"end line":658,
				"end column":46
			},
			{
				"start line":654,
				"start column":29,
				"end line":654,
				"end column":57
			},
			{
				"start line":646,
				"start column":29,
				"end line":646,
				"end column":46
			},
			{
				"start line":640,
				"start column":21,
				"end line":648,
				"end column":22
			},
			{
				"start line":655,
				"start column":29,
				"end line":655,
				"end column":46
			},
			{
				"start line":645,
				"start column":29,
				"end line":645,
				"end column":58
			},
			{
				"start line":652,
				"start column":21,
				"end line":660,
				"end column":22
			},
			{
				"start line":657,
				"start column":29,
				"end line":657,
				"end column":58
			}
		],
		"after location list":[
			{
				"start line":661,
				"start column":29,
				"end line":661,
				"end column":54
			},
			{
				"start line":648,
				"start column":29,
				"end line":648,
				"end column":54
			},
			{
				"start line":649,
				"start column":29,
				"end line":649,
				"end column":42
			},
			{
				"start line":658,
				"start column":29,
				"end line":658,
				"end column":53
			},
			{
				"start line":662,
				"start column":29,
				"end line":662,
				"end column":42
			},
			{
				"start line":659,
				"start column":29,
				"end line":659,
				"end column":42
			},
			{
				"start line":656,
				"start column":21,
				"end line":664,
				"end column":22
			},
			{
				"start line":643,
				"start column":21,
				"end line":651,
				"end column":22
			},
			{
				"start line":645,
				"start column":29,
				"end line":645,
				"end column":53
			}
		]
	},
	{
		"before commit":"50f252d10936fe92b5ae4fe6be747a593ac813a7",
		"after commit":"9a62d3c9ca6fc686aa0755545c7e52f406070df9",
		"file path":"core/src/main/java/hivemall/smile/classification/DecisionTree.java",
		"old name":"(int)x[i][j]",
		"new name":"x_ij",
		"type":"int",
		"variable place":{
			"start line":552,
			"start column":29,
			"end line":552,
			"end column":49
		},
		"before location list":[
			{
				"start line":516,
				"start column":29,
				"end line":516,
				"end column":45
			},
			{
				"start line":504,
				"start column":25,
				"end line":509,
				"end column":26
			},
			{
				"start line":505,
				"start column":29,
				"end line":505,
				"end column":45
			},
			{
				"start line":534,
				"start column":29,
				"end line":534,
				"end column":74
			},
			{
				"start line":540,
				"start column":25,
				"end line":540,
				"end column":41
			}
		],
		"after location list":[
			{
				"start line":595,
				"start column":25,
				"end line":600,
				"end column":26
			},
			{
				"start line":607,
				"start column":29,
				"end line":607,
				"end column":42
			},
			{
				"start line":626,
				"start column":29,
				"end line":626,
				"end column":73
			},
			{
				"start line":596,
				"start column":29,
				"end line":596,
				"end column":42
			},
			{
				"start line":632,
				"start column":25,
				"end line":632,
				"end column":38
			}
		]
	},
	{
		"before commit":"50f252d10936fe92b5ae4fe6be747a593ac813a7",
		"after commit":"9a62d3c9ca6fc686aa0755545c7e52f406070df9",
		"file path":"core/src/main/java/hivemall/smile/classification/DecisionTree.java",
		"old name":"y[i]",
		"new name":"y_i",
		"type":"int",
		"variable place":{
			"start line":593,
			"start column":35,
			"end line":593,
			"end column":45
		},
		"before location list":[
			{
				"start line":506,
				"start column":29,
				"end line":506,
				"end column":42
			},
			{
				"start line":542,
				"start column":25,
				"end line":542,
				"end column":55
			},
			{
				"start line":541,
				"start column":25,
				"end line":541,
				"end column":38
			},
			{
				"start line":507,
				"start column":29,
				"end line":507,
				"end column":59
			},
			{
				"start line":517,
				"start column":29,
				"end line":517,
				"end column":42
			},
			{
				"start line":518,
				"start column":29,
				"end line":518,
				"end column":59
			},
			{
				"start line":504,
				"start column":25,
				"end line":509,
				"end column":26
			}
		],
		"after location list":[
			{
				"start line":598,
				"start column":29,
				"end line":598,
				"end column":58
			},
			{
				"start line":634,
				"start column":25,
				"end line":634,
				"end column":54
			},
			{
				"start line":597,
				"start column":29,
				"end line":597,
				"end column":41
			},
			{
				"start line":633,
				"start column":25,
				"end line":633,
				"end column":37
			},
			{
				"start line":608,
				"start column":29,
				"end line":608,
				"end column":41
			},
			{
				"start line":595,
				"start column":25,
				"end line":600,
				"end column":26
			},
			{
				"start line":609,
				"start column":29,
				"end line":609,
				"end column":58
			}
		]
	},
	{
		"before commit":"50f252d10936fe92b5ae4fe6be747a593ac813a7",
		"after commit":"9a62d3c9ca6fc686aa0755545c7e52f406070df9",
		"file path":"core/src/main/java/hivemall/smile/classification/DecisionTree.java",
		"old name":"x[i][j]",
		"new name":"x_ij",
		"type":"double",
		"variable place":{
			"start line":592,
			"start column":38,
			"end line":592,
			"end column":52
		},
		"before location list":[
			{
				"start line":516,
				"start column":29,
				"end line":516,
				"end column":45
			},
			{
				"start line":504,
				"start column":25,
				"end line":509,
				"end column":26
			},
			{
				"start line":534,
				"start column":29,
				"end line":534,
				"end column":74
			},
			{
				"start line":505,
				"start column":29,
				"end line":505,
				"end column":45
			},
			{
				"start line":540,
				"start column":25,
				"end line":540,
				"end column":41
			}
		],
		"after location list":[
			{
				"start line":595,
				"start column":25,
				"end line":600,
				"end column":26
			},
			{
				"start line":626,
				"start column":29,
				"end line":626,
				"end column":73
			},
			{
				"start line":607,
				"start column":29,
				"end line":607,
				"end column":42
			},
			{
				"start line":596,
				"start column":29,
				"end line":596,
				"end column":42
			},
			{
				"start line":632,
				"start column":25,
				"end line":632,
				"end column":38
			}
		]
	},
	{
		"before commit":"93e2f34b28a6d5d3a169aa5a02648919fbd8f014",
		"after commit":"405f4ad84b993c9f84c6cee1eb23022c04bd1719",
		"file path":"src/main/java/hivemall/mf/OnlineMatrixFactorizationUDTF.java",
		"old name":"0.1d",
		"new name":"initStdDev",
		"type":"double",
		"variable place":{
			"start line":105,
			"start column":16,
			"end line":105,
			"end column":33
		},
		"before location list":[
			{
				"start line":114,
				"start column":13,
				"end line":114,
				"end column":55
			},
			{
				"start line":115,
				"start column":13,
				"end line":115,
				"end column":97
			},
			{
				"start line":116,
				"start column":13,
				"end line":116,
				"end column":98
			},
			{
				"start line":118,
				"start column":9,
				"end line":118,
				"end column":63
			}
		],
		"after location list":[
			{
				"start line":119,
				"start column":9,
				"end line":119,
				"end column":58
			},
			{
				"start line":115,
				"start column":13,
				"end line":115,
				"end column":93
			}
		]
	},
	{
		"before commit":"f25ef5c0bcf5a06efdd915fb3f7e7e2775ee8b45",
		"after commit":"db66bd4f2c34b6b9a6f2c0779334e3dfee9a795d",
		"file path":"src/main/java/hivemall/mf/OnlineMatrixFactorizationUDTF.java",
		"old name":"0.1d",
		"new name":"initStdDev",
		"type":"double",
		"variable place":{
			"start line":105,
			"start column":16,
			"end line":105,
			"end column":33
		},
		"before location list":[
			{
				"start line":114,
				"start column":13,
				"end line":114,
				"end column":55
			},
			{
				"start line":115,
				"start column":13,
				"end line":115,
				"end column":97
			},
			{
				"start line":116,
				"start column":13,
				"end line":116,
				"end column":98
			},
			{
				"start line":118,
				"start column":9,
				"end line":118,
				"end column":63
			}
		],
		"after location list":[
			{
				"start line":119,
				"start column":9,
				"end line":119,
				"end column":58
			},
			{
				"start line":115,
				"start column":13,
				"end line":115,
				"end column":93
			}
		]
	},
	{
		"before commit":"ee61d4670dd46010deb20520006c81a8d5d65f37",
		"after commit":"72ba94b65f22f91cda32291f706d706d931181ad",
		"file path":"src/main/hivemall/mix/server/MixServerHandler.java",
		"old name":"groupMap.putIfAbsent(groupID,map)",
		"new name":"existing",
		"type":"ConcurrentMap<Object,PartialResult>",
		"variable place":{
			"start line":69,
			"start column":50,
			"end line":69,
			"end column":95
		},
		"before location list":[
			{
				"start line":68,
				"start column":13,
				"end line":68,
				"end column":54
			},
			{
				"start line":85,
				"start column":13,
				"end line":85,
				"end column":57
			}
		],
		"after location list":[
			{
				"start line":91,
				"start column":17,
				"end line":91,
				"end column":36
			},
			{
				"start line":71,
				"start column":17,
				"end line":71,
				"end column":32
			}
		]
	},
	{
		"before commit":"ee61d4670dd46010deb20520006c81a8d5d65f37",
		"after commit":"72ba94b65f22f91cda32291f706d706d931181ad",
		"file path":"src/main/hivemall/mix/server/MixServerHandler.java",
		"old name":"map.putIfAbsent(feature,partial)",
		"new name":"existing",
		"type":"PartialResult",
		"variable place":{
			"start line":89,
			"start column":27,
			"end line":89,
			"end column":71
		},
		"before location list":[
			{
				"start line":68,
				"start column":13,
				"end line":68,
				"end column":54
			},
			{
				"start line":85,
				"start column":13,
				"end line":85,
				"end column":57
			}
		],
		"after location list":[
			{
				"start line":91,
				"start column":17,
				"end line":91,
				"end column":36
			},
			{
				"start line":71,
				"start column":17,
				"end line":71,
				"end column":32
			}
		]
	},
	{
		"before commit":"f118565a496d1552e8a71cc49a7a832696dc4c62",
		"after commit":"b123278f7d2d159232b4798435d71ce739de75cf",
		"file path":"src/main/hivemall/regression/OnlineRegressionUDTF.java",
		"old name":"dense_model ? PrimitiveObjectInspectorFactory.javaIntObjectInspector : featureInputOI",
		"new name":"featureOutputOI",
		"type":"PrimitiveObjectInspector",
		"variable place":{
			"start line":77,
			"start column":34,
			"end line":78,
			"end column":33
		},
		"before location list":[
			{
				"start line":85,
				"start column":9,
				"end line":85,
				"end column":44
			},
			{
				"start line":81,
				"start column":13,
				"end line":81,
				"end column":76
			}
		],
		"after location list":[
			{
				"start line":85,
				"start column":9,
				"end line":85,
				"end column":45
			},
			{
				"start line":81,
				"start column":13,
				"end line":81,
				"end column":77
			}
		]
	}
]