[
	{
		"class name":"javax.crypto.spec.GCMParameterSpec",
		"method name":"getTLen",
		"method key":"Ljavax/crypto/spec/GCMParameterSpec;.getTLen()I",
		"read list":[
			{
				"name":"javax.crypto.spec.GCMParameterSpec.tLen",
				"static label":0
			}
		],
		"write list":[],
		"native method list":[]
	},
	{
		"class name":"javax.crypto.spec.GCMParameterSpec",
		"method name":"getIV",
		"method key":"Ljavax/crypto/spec/GCMParameterSpec;.getIV()[B",
		"read list":[],
		"write list":[],
		"native method list":[
			{
				"name":"java.lang.Object.clone",
				"static label":0
			}
		]
	}
]