[
	{
		"class name":"javax.crypto.KeyGenerator",
		"method name":"disableFailover",
		"method key":"Ljavax/crypto/KeyGenerator;.disableFailover()V",
		"read list":[
			{
				"name":"javax.crypto.KeyGenerator.initParams",
				"static label":0
			},
			{
				"name":"javax.crypto.KeyGenerator.initType",
				"static label":0
			},
			{
				"name":"javax.crypto.KeyGenerator.serviceIterator",
				"static label":0
			},
			{
				"name":"javax.crypto.KeyGenerator.initRandom",
				"static label":0
			}
		],
		"write list":[
			{
				"name":"javax.crypto.KeyGenerator.initParams",
				"static label":0
			},
			{
				"name":"javax.crypto.KeyGenerator.initType",
				"static label":0
			},
			{
				"name":"javax.crypto.KeyGenerator.serviceIterator",
				"static label":0
			},
			{
				"name":"javax.crypto.KeyGenerator.initRandom",
				"static label":0
			}
		],
		"native method list":[]
	}
]