[
	{
		"class name":"sun.rmi.transport.Target",
		"method name":"getStub",
		"method key":"Lsun/rmi/transport/Target;.getStub()Ljava/rmi/Remote;",
		"read list":[
			{
				"name":"sun.rmi.transport.Target.stub",
				"static label":0
			}
		],
		"write list":[],
		"native method list":[]
	},
	{
		"class name":"sun.rmi.transport.Target",
		"method name":"getObjectEndpoint",
		"method key":"Lsun/rmi/transport/Target;.getObjectEndpoint()Lsun/rmi/transport/ObjectEndpoint;",
		"read list":[
			{
				"name":"space.java.rmi.server.UID.time",
				"static label":0
			},
			{
				"name":"sun.rmi.transport.ObjectEndpoint.id",
				"static label":0
			},
			{
				"name":"id.java.rmi.server.ObjID.space",
				"static label":0
			},
			{
				"name":"sun.rmi.transport.Target.exportedTransport",
				"static label":0
			},
			{
				"name":"space.java.rmi.server.UID.count",
				"static label":0
			},
			{
				"name":"java.rmi.server.ObjID.DGC_ID",
				"static label":1
			},
			{
				"name":"space.java.rmi.server.UID.unique",
				"static label":0
			},
			{
				"name":"sun.rmi.transport.Target.id",
				"static label":0
			},
			{
				"name":"id.java.rmi.server.ObjID.objNum",
				"static label":0
			}
		],
		"write list":[],
		"native method list":[]
	},
	{
		"class name":"sun.rmi.transport.Target",
		"method name":"getWeakImpl",
		"method key":"Lsun/rmi/transport/Target;.getWeakImpl()Lsun/rmi/transport/WeakRef;",
		"read list":[
			{
				"name":"sun.rmi.transport.Target.weakImpl",
				"static label":0
			}
		],
		"write list":[],
		"native method list":[]
	},
	{
		"class name":"sun.rmi.transport.Target",
		"method name":"getDispatcher",
		"method key":"Lsun/rmi/transport/Target;.getDispatcher()Lsun/rmi/server/Dispatcher;",
		"read list":[
			{
				"name":"sun.rmi.transport.Target.disp",
				"static label":0
			}
		],
		"write list":[],
		"native method list":[]
	},
	{
		"class name":"sun.rmi.transport.Target",
		"method name":"getAccessControlContext",
		"method key":"Lsun/rmi/transport/Target;.getAccessControlContext()Ljava/security/AccessControlContext;",
		"read list":[
			{
				"name":"sun.rmi.transport.Target.acc",
				"static label":0
			}
		],
		"write list":[],
		"native method list":[]
	},
	{
		"class name":"sun.rmi.transport.Target",
		"method name":"getContextClassLoader",
		"method key":"Lsun/rmi/transport/Target;.getContextClassLoader()Ljava/lang/ClassLoader;",
		"read list":[
			{
				"name":"sun.rmi.transport.Target.ccl",
				"static label":0
			}
		],
		"write list":[],
		"native method list":[]
	},
	{
		"class name":"sun.rmi.transport.Target",
		"method name":"getImpl",
		"method key":"Lsun/rmi/transport/Target;.getImpl()Ljava/rmi/Remote;",
		"read list":[
			{
				"name":"sun.rmi.transport.Target.weakImpl",
				"static label":0
			},
			{
				"name":"weakImpl.java.lang.ref.Reference<T>.referent",
				"static label":0
			}
		],
		"write list":[],
		"native method list":[]
	},
	{
		"class name":"sun.rmi.transport.Target",
		"method name":"isPermanent",
		"method key":"Lsun/rmi/transport/Target;.isPermanent()Z",
		"read list":[
			{
				"name":"sun.rmi.transport.Target.permanent",
				"static label":0
			}
		],
		"write list":[],
		"native method list":[]
	},
	{
		"class name":"sun.rmi.transport.Target",
		"method name":"pinImpl",
		"method key":"Lsun/rmi/transport/Target;.pinImpl()V",
		"read list":[
			{
				"name":"weakImpl.sun.rmi.transport.WeakRef.strongRef",
				"static label":0
			},
			{
				"name":"sun.rmi.runtime.Log.VERBOSE",
				"static label":1
			},
			{
				"name":"sun.rmi.transport.Target.weakImpl",
				"static label":0
			},
			{
				"name":"sun.rmi.transport.DGCImpl.dgcLog",
				"static label":1
			}
		],
		"write list":[
			{
				"name":"weakImpl.sun.rmi.transport.WeakRef.strongRef",
				"static label":0
			}
		],
		"native method list":[]
	},
	{
		"class name":"sun.rmi.transport.Target",
		"method name":"unpinImpl",
		"method key":"Lsun/rmi/transport/Target;.unpinImpl()V",
		"read list":[
			{
				"name":"weakImpl.sun.rmi.transport.WeakRef.strongRef",
				"static label":0
			},
			{
				"name":"sun.rmi.runtime.Log.VERBOSE",
				"static label":1
			},
			{
				"name":"sun.rmi.transport.Target.weakImpl",
				"static label":0
			},
			{
				"name":"sun.rmi.transport.Target.refSet",
				"static label":0
			},
			{
				"name":"sun.rmi.transport.DGCImpl.dgcLog",
				"static label":1
			},
			{
				"name":"sun.rmi.transport.Target.permanent",
				"static label":0
			}
		],
		"write list":[
			{
				"name":"weakImpl.sun.rmi.transport.WeakRef.strongRef",
				"static label":0
			},
			{
				"name":"sun.rmi.transport.Target.permanent",
				"static label":0
			}
		],
		"native method list":[]
	},
	{
		"class name":"sun.rmi.transport.Target",
		"method name":"setExportedTransport",
		"method key":"Lsun/rmi/transport/Target;.setExportedTransport(Lsun/rmi/transport/Transport;)V",
		"read list":[
			{
				"name":"sun.rmi.transport.Target.exportedTransport",
				"static label":0
			}
		],
		"write list":[],
		"native method list":[]
	},
	{
		"class name":"sun.rmi.transport.Target",
		"method name":"referenced",
		"method key":"Lsun/rmi/transport/Target;.referenced(JLjava/rmi/dgc/VMID;)V",
		"read list":[
			{
				"name":"DGCImpl.getDGCImpl().sun.rmi.transport.DGCImpl.leaseTable",
				"static label":0
			},
			{
				"name":"t.java.lang.Thread.threadStatus",
				"static label":0
			},
			{
				"name":"sun.rmi.runtime.Log.BRIEF",
				"static label":1
			},
			{
				"name":"group.java.lang.ThreadGroup.destroyed",
				"static label":0
			},
			{
				"name":"sun.rmi.transport.DGCImpl.dgcLog",
				"static label":1
			},
			{
				"name":"sun.rmi.transport.Target.nextThreadNum",
				"static label":1
			},
			{
				"name":"java.util.Hashtable<K,V>.MAX_ARRAY_SIZE",
				"static label":1
			},
			{
				"name":"group.java.lang.ThreadGroup.nthreads",
				"static label":0
			},
			{
				"name":"weakImpl.sun.rmi.transport.WeakRef.strongRef",
				"static label":0
			},
			{
				"name":"sun.rmi.runtime.Log.VERBOSE",
				"static label":1
			},
			{
				"name":"sun.rmi.transport.Target.weakImpl",
				"static label":0
			},
			{
				"name":"java.lang.Integer.MAX_VALUE",
				"static label":1
			},
			{
				"name":"t.java.lang.Thread.group",
				"static label":0
			},
			{
				"name":"sun.rmi.transport.Target.sequenceTable",
				"static label":0
			},
			{
				"name":"sun.rmi.transport.Target.refSet",
				"static label":0
			},
			{
				"name":"entry.sun.rmi.transport.SequenceEntry.sequenceNum",
				"static label":0
			},
			{
				"name":"group.java.lang.ThreadGroup.nUnstartedThreads",
				"static label":0
			},
			{
				"name":"target.sun.rmi.transport.Target.sequenceTable",
				"static label":0
			},
			{
				"name":"sun.rmi.transport.DGCImpl.dgc",
				"static label":1
			},
			{
				"name":"java.util.Vector<E>.MAX_ARRAY_SIZE",
				"static label":1
			}
		],
		"write list":[
			{
				"name":"group.java.lang.ThreadGroup.nthreads",
				"static label":0
			},
			{
				"name":"weakImpl.sun.rmi.transport.WeakRef.strongRef",
				"static label":0
			},
			{
				"name":"target.sun.rmi.transport.Target.permanent",
				"static label":0
			},
			{
				"name":"group.java.lang.ThreadGroup.nUnstartedThreads",
				"static label":0
			}
		],
		"native method list":[
			{
				"name":"java.lang.System.arraycopy",
				"static label":1
			},
			{
				"name":"java.security.AccessController.doPrivileged",
				"static label":1
			},
			{
				"name":"java.lang.Thread.start0",
				"static label":0
			},
			{
				"name":"java.lang.Object.hashCode",
				"static label":0
			}
		]
	},
	{
		"class name":"sun.rmi.transport.Target",
		"method name":"unreferenced",
		"method key":"Lsun/rmi/transport/Target;.unreferenced(JLjava/rmi/dgc/VMID;Z)V",
		"read list":[
			{
				"name":"DGCImpl.getDGCImpl().sun.rmi.transport.DGCImpl.leaseTable",
				"static label":0
			},
			{
				"name":"weakImpl.java.lang.ref.Reference<T>.referent",
				"static label":0
			},
			{
				"name":"t.java.lang.Thread.threadStatus",
				"static label":0
			},
			{
				"name":"group.java.lang.ThreadGroup.destroyed",
				"static label":0
			},
			{
				"name":"sun.rmi.transport.DGCImpl.dgcLog",
				"static label":1
			},
			{
				"name":"sun.rmi.transport.Target.nextThreadNum",
				"static label":1
			},
			{
				"name":"sun.rmi.transport.Target.permanent",
				"static label":0
			},
			{
				"name":"group.java.lang.ThreadGroup.nthreads",
				"static label":0
			},
			{
				"name":"weakImpl.sun.rmi.transport.WeakRef.strongRef",
				"static label":0
			},
			{
				"name":"sun.rmi.runtime.Log.VERBOSE",
				"static label":1
			},
			{
				"name":"sun.rmi.transport.Target.weakImpl",
				"static label":0
			},
			{
				"name":"t.java.lang.Thread.group",
				"static label":0
			},
			{
				"name":"sun.rmi.transport.Target.sequenceTable",
				"static label":0
			},
			{
				"name":"sun.rmi.transport.Target.refSet",
				"static label":0
			},
			{
				"name":"entry.sun.rmi.transport.SequenceEntry.sequenceNum",
				"static label":0
			},
			{
				"name":"group.java.lang.ThreadGroup.nUnstartedThreads",
				"static label":0
			},
			{
				"name":"entry.sun.rmi.transport.SequenceEntry.keep",
				"static label":0
			},
			{
				"name":"sun.rmi.transport.DGCImpl.dgc",
				"static label":1
			}
		],
		"write list":[
			{
				"name":"group.java.lang.ThreadGroup.nthreads",
				"static label":0
			},
			{
				"name":"weakImpl.sun.rmi.transport.WeakRef.strongRef",
				"static label":0
			},
			{
				"name":"group.java.lang.ThreadGroup.nUnstartedThreads",
				"static label":0
			},
			{
				"name":"entry.sun.rmi.transport.SequenceEntry.keep",
				"static label":0
			},
			{
				"name":"sun.rmi.transport.Target.permanent",
				"static label":0
			}
		],
		"native method list":[
			{
				"name":"java.lang.System.arraycopy",
				"static label":1
			},
			{
				"name":"java.security.AccessController.doPrivileged",
				"static label":1
			},
			{
				"name":"java.lang.Thread.start0",
				"static label":0
			},
			{
				"name":"java.lang.Object.hashCode",
				"static label":0
			}
		]
	},
	{
		"class name":"sun.rmi.transport.Target",
		"method name":"unexport",
		"method key":"Lsun/rmi/transport/Target;.unexport(Z)Z",
		"read list":[
			{
				"name":"weakImpl.sun.rmi.transport.WeakRef.strongRef",
				"static label":0
			},
			{
				"name":"sun.rmi.runtime.Log.VERBOSE",
				"static label":1
			},
			{
				"name":"sun.rmi.transport.Target.disp",
				"static label":0
			},
			{
				"name":"sun.rmi.transport.Target.weakImpl",
				"static label":0
			},
			{
				"name":"dgc.sun.rmi.transport.DGCImpl.leaseTable",
				"static label":0
			},
			{
				"name":"sun.rmi.transport.Target.refSet",
				"static label":0
			},
			{
				"name":"sun.rmi.transport.DGCImpl.dgcLog",
				"static label":1
			},
			{
				"name":"sun.rmi.transport.Target.callCount",
				"static label":0
			},
			{
				"name":"sun.rmi.transport.Target.permanent",
				"static label":0
			},
			{
				"name":"sun.rmi.transport.DGCImpl.dgc",
				"static label":1
			}
		],
		"write list":[
			{
				"name":"weakImpl.sun.rmi.transport.WeakRef.strongRef",
				"static label":0
			},
			{
				"name":"sun.rmi.transport.Target.disp",
				"static label":0
			},
			{
				"name":"sun.rmi.transport.Target.permanent",
				"static label":0
			}
		],
		"native method list":[]
	},
	{
		"class name":"sun.rmi.transport.Target",
		"method name":"markRemoved",
		"method key":"Lsun/rmi/transport/Target;.markRemoved()V",
		"read list":[
			{
				"name":"sun.rmi.transport.ObjectTable.gcLatencyRequest",
				"static label":1
			},
			{
				"name":"sun.rmi.transport.ObjectTable.keepAliveLock",
				"static label":1
			},
			{
				"name":"sun.rmi.transport.Target.callCount",
				"static label":0
			},
			{
				"name":"sun.rmi.transport.Target.exportedTransport",
				"static label":0
			},
			{
				"name":"sun.rmi.transport.Target.removed",
				"static label":0
			},
			{
				"name":"sun.rmi.transport.ObjectTable.keepAliveCount",
				"static label":1
			},
			{
				"name":"sun.rmi.transport.Target.permanent",
				"static label":0
			},
			{
				"name":"sun.rmi.transport.ObjectTable.reaper",
				"static label":1
			}
		],
		"write list":[
			{
				"name":"sun.rmi.transport.ObjectTable.gcLatencyRequest",
				"static label":1
			},
			{
				"name":"sun.rmi.transport.Target.removed",
				"static label":0
			},
			{
				"name":"sun.rmi.transport.ObjectTable.keepAliveCount",
				"static label":1
			},
			{
				"name":"sun.rmi.transport.Target.permanent",
				"static label":0
			},
			{
				"name":"sun.rmi.transport.ObjectTable.reaper",
				"static label":1
			}
		],
		"native method list":[
			{
				"name":"java.security.AccessController.doPrivileged",
				"static label":1
			}
		]
	},
	{
		"class name":"sun.rmi.transport.Target",
		"method name":"incrementCallCount",
		"method key":"Lsun/rmi/transport/Target;.incrementCallCount()V|Ljava/rmi/NoSuchObjectException;",
		"read list":[
			{
				"name":"sun.rmi.transport.Target.disp",
				"static label":0
			},
			{
				"name":"sun.rmi.transport.Target.callCount",
				"static label":0
			}
		],
		"write list":[
			{
				"name":"sun.rmi.transport.Target.callCount",
				"static label":0
			}
		],
		"native method list":[]
	},
	{
		"class name":"sun.rmi.transport.Target",
		"method name":"decrementCallCount",
		"method key":"Lsun/rmi/transport/Target;.decrementCallCount()V",
		"read list":[
			{
				"name":"sun.rmi.transport.ObjectTable.gcLatencyRequest",
				"static label":1
			},
			{
				"name":"sun.rmi.transport.ObjectTable.keepAliveLock",
				"static label":1
			},
			{
				"name":"sun.rmi.transport.Target.callCount",
				"static label":0
			},
			{
				"name":"sun.rmi.transport.Target.removed",
				"static label":0
			},
			{
				"name":"sun.rmi.transport.ObjectTable.keepAliveCount",
				"static label":1
			},
			{
				"name":"sun.rmi.transport.Target.permanent",
				"static label":0
			},
			{
				"name":"sun.rmi.transport.ObjectTable.reaper",
				"static label":1
			}
		],
		"write list":[
			{
				"name":"sun.rmi.transport.ObjectTable.gcLatencyRequest",
				"static label":1
			},
			{
				"name":"sun.rmi.transport.Target.callCount",
				"static label":0
			},
			{
				"name":"sun.rmi.transport.ObjectTable.keepAliveCount",
				"static label":1
			},
			{
				"name":"sun.rmi.transport.Target.permanent",
				"static label":0
			},
			{
				"name":"sun.rmi.transport.ObjectTable.reaper",
				"static label":1
			}
		],
		"native method list":[
			{
				"name":"java.security.AccessController.doPrivileged",
				"static label":1
			}
		]
	},
	{
		"class name":"sun.rmi.transport.Target",
		"method name":"isEmpty",
		"method key":"Lsun/rmi/transport/Target;.isEmpty()Z",
		"read list":[
			{
				"name":"sun.rmi.transport.Target.refSet",
				"static label":0
			}
		],
		"write list":[],
		"native method list":[]
	},
	{
		"class name":"sun.rmi.transport.Target",
		"method name":"vmidDead",
		"method key":"Lsun/rmi/transport/Target;.vmidDead(Ljava/rmi/dgc/VMID;)V",
		"read list":[
			{
				"name":"DGCImpl.getDGCImpl().sun.rmi.transport.DGCImpl.leaseTable",
				"static label":0
			},
			{
				"name":"weakImpl.java.lang.ref.Reference<T>.referent",
				"static label":0
			},
			{
				"name":"t.java.lang.Thread.threadStatus",
				"static label":0
			},
			{
				"name":"sun.rmi.runtime.Log.BRIEF",
				"static label":1
			},
			{
				"name":"group.java.lang.ThreadGroup.destroyed",
				"static label":0
			},
			{
				"name":"sun.rmi.transport.DGCImpl.dgcLog",
				"static label":1
			},
			{
				"name":"sun.rmi.transport.Target.nextThreadNum",
				"static label":1
			},
			{
				"name":"sun.rmi.transport.Target.permanent",
				"static label":0
			},
			{
				"name":"group.java.lang.ThreadGroup.nthreads",
				"static label":0
			},
			{
				"name":"weakImpl.sun.rmi.transport.WeakRef.strongRef",
				"static label":0
			},
			{
				"name":"sun.rmi.runtime.Log.VERBOSE",
				"static label":1
			},
			{
				"name":"sun.rmi.transport.Target.weakImpl",
				"static label":0
			},
			{
				"name":"t.java.lang.Thread.group",
				"static label":0
			},
			{
				"name":"sun.rmi.transport.Target.sequenceTable",
				"static label":0
			},
			{
				"name":"sun.rmi.transport.Target.refSet",
				"static label":0
			},
			{
				"name":"group.java.lang.ThreadGroup.nUnstartedThreads",
				"static label":0
			},
			{
				"name":"sun.rmi.transport.DGCImpl.dgc",
				"static label":1
			}
		],
		"write list":[
			{
				"name":"group.java.lang.ThreadGroup.nthreads",
				"static label":0
			},
			{
				"name":"weakImpl.sun.rmi.transport.WeakRef.strongRef",
				"static label":0
			},
			{
				"name":"group.java.lang.ThreadGroup.nUnstartedThreads",
				"static label":0
			},
			{
				"name":"sun.rmi.transport.Target.permanent",
				"static label":0
			}
		],
		"native method list":[
			{
				"name":"java.lang.System.arraycopy",
				"static label":1
			},
			{
				"name":"java.security.AccessController.doPrivileged",
				"static label":1
			},
			{
				"name":"java.lang.Thread.start0",
				"static label":0
			},
			{
				"name":"java.lang.Object.hashCode",
				"static label":0
			}
		]
	},
	{
		"class name":"sun.rmi.transport.SequenceEntry",
		"method name":"retain",
		"method key":"Lsun/rmi/transport/SequenceEntry;.retain(J)V",
		"read list":[
			{
				"name":"sun.rmi.transport.SequenceEntry.keep",
				"static label":0
			},
			{
				"name":"sun.rmi.transport.SequenceEntry.sequenceNum",
				"static label":0
			}
		],
		"write list":[
			{
				"name":"sun.rmi.transport.SequenceEntry.keep",
				"static label":0
			}
		],
		"native method list":[]
	},
	{
		"class name":"sun.rmi.transport.SequenceEntry",
		"method name":"update",
		"method key":"Lsun/rmi/transport/SequenceEntry;.update(J)V",
		"read list":[
			{
				"name":"sun.rmi.transport.SequenceEntry.sequenceNum",
				"static label":0
			}
		],
		"write list":[],
		"native method list":[]
	}
]