[
	{
		"class name":"java.applet.AppletContext",
		"method name":"getAudioClip",
		"method key":"Ljava/applet/AppletContext;.getAudioClip(Ljava/net/URL;)Ljava/applet/AudioClip;",
		"read list":[],
		"write list":[],
		"native method list":[]
	},
	{
		"class name":"java.applet.AppletContext",
		"method name":"getImage",
		"method key":"Ljava/applet/AppletContext;.getImage(Ljava/net/URL;)Ljava/awt/Image;",
		"read list":[],
		"write list":[],
		"native method list":[]
	},
	{
		"class name":"java.applet.AppletContext",
		"method name":"getApplet",
		"method key":"Ljava/applet/AppletContext;.getApplet(Ljava/lang/String;)Ljava/applet/Applet;",
		"read list":[],
		"write list":[],
		"native method list":[]
	},
	{
		"class name":"java.applet.AppletContext",
		"method name":"getApplets",
		"method key":"Ljava/applet/AppletContext;.getApplets()Ljava/util/Enumeration<Ljava/applet/Applet;>;",
		"read list":[],
		"write list":[],
		"native method list":[]
	},
	{
		"class name":"java.applet.AppletContext",
		"method name":"showDocument",
		"method key":"Ljava/applet/AppletContext;.showDocument(Ljava/net/URL;)V",
		"read list":[],
		"write list":[],
		"native method list":[]
	},
	{
		"class name":"java.applet.AppletContext",
		"method name":"showDocument",
		"method key":"Ljava/applet/AppletContext;.showDocument(Ljava/net/URL;Ljava/lang/String;)V",
		"read list":[],
		"write list":[],
		"native method list":[]
	},
	{
		"class name":"java.applet.AppletContext",
		"method name":"showStatus",
		"method key":"Ljava/applet/AppletContext;.showStatus(Ljava/lang/String;)V",
		"read list":[],
		"write list":[],
		"native method list":[]
	},
	{
		"class name":"java.applet.AppletContext",
		"method name":"setStream",
		"method key":"Ljava/applet/AppletContext;.setStream(Ljava/lang/String;Ljava/io/InputStream;)V|Ljava/io/IOException;",
		"read list":[],
		"write list":[],
		"native method list":[]
	},
	{
		"class name":"java.applet.AppletContext",
		"method name":"getStream",
		"method key":"Ljava/applet/AppletContext;.getStream(Ljava/lang/String;)Ljava/io/InputStream;",
		"read list":[],
		"write list":[],
		"native method list":[]
	},
	{
		"class name":"java.applet.AppletContext",
		"method name":"getStreamKeys",
		"method key":"Ljava/applet/AppletContext;.getStreamKeys()Ljava/util/Iterator<Ljava/lang/String;>;",
		"read list":[],
		"write list":[],
		"native method list":[]
	}
]